django_amqp/__init__.py
django_amqp/apps.py
django_amqp/backend.py
django_amqp/service_bus.py
django_amqp/utils.py
django_amqp/management/__init__.py
django_amqp/management/commands/amqp_worker.py
django_amqp-0.1.1a1.dist-info/licenses/LICENSE
django_amqp-0.1.1a1.dist-info/METADATA
django_amqp-0.1.1a1.dist-info/WHEEL
django_amqp-0.1.1a1.dist-info/top_level.txt
django_amqp-0.1.1a1.dist-info/RECORD
