Metadata-Version: 2.4
Name: django-amqp
Version: 0.1.1a1
Summary: AMQP support for django. Supporting RabbitMQ and Azure ServiceBus.
Author-email: Karl Hobley <karl@kaed.uk>
License-Expression: BSD-3-Clause
Classifier: Development Status :: 5 - Production/Stable
Classifier: Environment :: Web Environment
Classifier: Framework :: Django
Classifier: Intended Audience :: Developers
Classifier: Operating System :: OS Independent
Classifier: Programming Language :: Python
Classifier: Programming Language :: Python :: 3
Classifier: Programming Language :: Python :: 3 :: Only
Classifier: Programming Language :: Python :: 3.12
Classifier: Programming Language :: Python :: 3.13
Classifier: Programming Language :: Python :: 3.14
Classifier: Topic :: Software Development :: Libraries :: Python Modules
Requires-Python: >=3.12
License-File: LICENSE
Requires-Dist: azure-servicebus>=7.14.3
Requires-Dist: Django<7,>=6.0
Requires-Dist: pydantic>=2.12.5
Dynamic: license-file
